{
    "Id": 169,
    "Title": "Autumn Term Elections 2023",
    "Organisation": {
        "Id": 6013,
        "Name": "University of Birmingham Guild of Students",
        "GroupingType": null,
        "Organisation": null,
        "FullName": "University of Birmingham Guild of Students"
    },
    "Eligible": 40945,
    "Voters": 552,
    "NonVoters": 40393,
    "Votes": 3243,
    "PostCount": 75,
    "CandidateCount": 82,
    "IndividualCandidateCount": 53,
    "DateGenerated": "2023-10-12T23:30:15.747341+01:00",
    "Groups": [
        {
            "Name": "Age range",
            "Items": [
                {
                    "Name": "16 - 17",
                    "Voters": 3,
                    "NonVoters": 306,
                    "Eligible": 309,
                    "IsOtherItem": false,
                    "Turnout": 0.970873786407767,
                    "RelativeTurnout": 0.00732690194162902
                },
                {
                    "Name": "18 - 21",
                    "Voters": 330,
                    "NonVoters": 23225,
                    "Eligible": 23555,
                    "IsOtherItem": false,
                    "Turnout": 1.40097643812354,
                    "RelativeTurnout": 0.805959213579192
                },
                {
                    "Name": "22 - 25",
                    "Voters": 145,
                    "NonVoters": 8176,
                    "Eligible": 8321,
                    "IsOtherItem": false,
                    "Turnout": 1.74257901694508,
                    "RelativeTurnout": 0.354133593845402
                },
                {
                    "Name": "26 - 30",
                    "Voters": 50,
                    "NonVoters": 3296,
                    "Eligible": 3346,
                    "IsOtherItem": false,
                    "Turnout": 1.49432157800359,
                    "RelativeTurnout": 0.122115032360484
                },
                {
                    "Name": "All other values",
                    "Voters": 0,
                    "NonVoters": 2,
                    "Eligible": 2,
                    "IsOtherItem": true,
                    "Turnout": 0.0,
                    "RelativeTurnout": 0.0
                },
                {
                    "Name": "Over 30",
                    "Voters": 24,
                    "NonVoters": 5382,
                    "Eligible": 5406,
                    "IsOtherItem": false,
                    "Turnout": 0.443951165371809,
                    "RelativeTurnout": 0.0586152155330321
                },
                {
                    "Name": "Unknown",
                    "Voters": 0,
                    "NonVoters": 6,
                    "Eligible": 6,
                    "IsOtherItem": false,
                    "Turnout": 0.0,
                    "RelativeTurnout": 0.0
                }
            ]
        },
        {
            "Name": "Sex",
            "Items": [
                {
                    "Name": "All other values",
                    "Voters": 0,
                    "NonVoters": 3,
                    "Eligible": 3,
                    "IsOtherItem": true,
                    "Turnout": 0.0,
                    "RelativeTurnout": 0.0
                },
                {
                    "Name": "F",
                    "Voters": 260,
                    "NonVoters": 22966,
                    "Eligible": 23226,
                    "IsOtherItem": false,
                    "Turnout": 1.11943511581848,
                    "RelativeTurnout": 0.634998168274515
                },
                {
                    "Name": "M",
                    "Voters": 290,
                    "NonVoters": 17321,
                    "Eligible": 17611,
                    "IsOtherItem": false,
                    "Turnout": 1.64669808642326,
                    "RelativeTurnout": 0.708267187690805
                },
                {
                    "Name": "N",
                    "Voters": 2,
                    "NonVoters": 103,
                    "Eligible": 105,
                    "IsOtherItem": false,
                    "Turnout": 1.9047619047619,
                    "RelativeTurnout": 0.00488460129441934
                }
            ]
        },
        {
            "Name": "Student type",
            "Items": [
                {
                    "Name": "All other values",
                    "Voters": 0,
                    "NonVoters": 1,
                    "Eligible": 1,
                    "IsOtherItem": true,
                    "Turnout": 0.0,
                    "RelativeTurnout": 0.0
                },
                {
                    "Name": "Postgraduate Research",
                    "Voters": 20,
                    "NonVoters": 3854,
                    "Eligible": 3874,
                    "IsOtherItem": false,
                    "Turnout": 0.516262261228704,
                    "RelativeTurnout": 0.0488460129441934
                },
                {
                    "Name": "Postgraduate Taught",
                    "Voters": 176,
                    "NonVoters": 9700,
                    "Eligible": 9876,
                    "IsOtherItem": false,
                    "Turnout": 1.78209801539085,
                    "RelativeTurnout": 0.429844913908902
                },
                {
                    "Name": "Undergraduate",
                    "Voters": 356,
                    "NonVoters": 26838,
                    "Eligible": 27194,
                    "IsOtherItem": false,
                    "Turnout": 1.30911230418475,
                    "RelativeTurnout": 0.869459030406643
                }
            ]
        },
        {
            "Name": "Year of study",
            "Items": [
                {
                    "Name": "1st year",
                    "Voters": 324,
                    "NonVoters": 17195,
                    "Eligible": 17519,
                    "IsOtherItem": false,
                    "Turnout": 1.84942062903134,
                    "RelativeTurnout": 0.791305409695934
                },
                {
                    "Name": "2nd year",
                    "Voters": 117,
                    "NonVoters": 9310,
                    "Eligible": 9427,
                    "IsOtherItem": false,
                    "Turnout": 1.24111594356635,
                    "RelativeTurnout": 0.285749175723532
                },
                {
                    "Name": "3rd year",
                    "Voters": 76,
                    "NonVoters": 9092,
                    "Eligible": 9168,
                    "IsOtherItem": false,
                    "Turnout": 0.828970331588133,
                    "RelativeTurnout": 0.185614849187935
                },
                {
                    "Name": "4th year",
                    "Voters": 23,
                    "NonVoters": 3190,
                    "Eligible": 3213,
                    "IsOtherItem": false,
                    "Turnout": 0.71584189231248,
                    "RelativeTurnout": 0.0561729148858224
                },
                {
                    "Name": "5th year",
                    "Voters": 5,
                    "NonVoters": 803,
                    "Eligible": 808,
                    "IsOtherItem": false,
                    "Turnout": 0.618811881188119,
                    "RelativeTurnout": 0.0122115032360484
                },
                {
                    "Name": "6th year",
                    "Voters": 0,
                    "NonVoters": 122,
                    "Eligible": 122,
                    "IsOtherItem": false,
                    "Turnout": 0.0,
                    "RelativeTurnout": 0.0
                },
                {
                    "Name": "7th year",
                    "Voters": 0,
                    "NonVoters": 71,
                    "Eligible": 71,
                    "IsOtherItem": false,
                    "Turnout": 0.0,
                    "RelativeTurnout": 0.0
                },
                {
                    "Name": "8th year",
                    "Voters": 0,
                    "NonVoters": 34,
                    "Eligible": 34,
                    "IsOtherItem": false,
                    "Turnout": 0.0,
                    "RelativeTurnout": 0.0
                },
                {
                    "Name": "9th year",
                    "Voters": 1,
                    "NonVoters": 15,
                    "Eligible": 16,
                    "IsOtherItem": false,
                    "Turnout": 6.25,
                    "RelativeTurnout": 0.00244230064720967
                },
                {
                    "Name": "All other values",
                    "Voters": 0,
                    "NonVoters": 1,
                    "Eligible": 1,
                    "IsOtherItem": true,
                    "Turnout": 0.0,
                    "RelativeTurnout": 0.0
                },
                {
                    "Name": "Foundation year",
                    "Voters": 6,
                    "NonVoters": 560,
                    "Eligible": 566,
                    "IsOtherItem": false,
                    "Turnout": 1.06007067137809,
                    "RelativeTurnout": 0.014653803883258
                }
            ]
        },
        {
            "Name": "Department",
            "Items": [
                {
                    "Name": "Academic Services",
                    "Voters": 3,
                    "NonVoters": 3,
                    "Eligible": 6,
                    "IsOtherItem": false,
                    "Turnout": 50.0,
                    "RelativeTurnout": 0.00732690194162902
                },
                {
                    "Name": "Accounting",
                    "Voters": 15,
                    "NonVoters": 1081,
                    "Eligible": 1096,
                    "IsOtherItem": false,
                    "Turnout": 1.36861313868613,
                    "RelativeTurnout": 0.0366345097081451
                },
                {
                    "Name": "African Studies & Anthropology",
                    "Voters": 4,
                    "NonVoters": 86,
                    "Eligible": 90,
                    "IsOtherItem": false,
                    "Turnout": 4.44444444444444,
                    "RelativeTurnout": 0.00976920258883869
                },
                {
                    "Name": "All other values",
                    "Voters": 0,
                    "NonVoters": 120,
                    "Eligible": 120,
                    "IsOtherItem": true,
                    "Turnout": 0.0,
                    "RelativeTurnout": 0.0
                },
                {
                    "Name": "Art Hist, Cur and Vis Studies",
                    "Voters": 1,
                    "NonVoters": 152,
                    "Eligible": 153,
                    "IsOtherItem": false,
                    "Turnout": 0.65359477124183,
                    "RelativeTurnout": 0.00244230064720967
                },
                {
                    "Name": "Bhm Clinical Trial Unit (BCTU)",
                    "Voters": 1,
                    "NonVoters": 14,
                    "Eligible": 15,
                    "IsOtherItem": false,
                    "Turnout": 6.66666666666667,
                    "RelativeTurnout": 0.00244230064720967
                },
                {
                    "Name": "Biomedical Sciences",
                    "Voters": 7,
                    "NonVoters": 643,
                    "Eligible": 650,
                    "IsOtherItem": false,
                    "Turnout": 1.07692307692308,
                    "RelativeTurnout": 0.0170961045304677
                },
                {
                    "Name": "Birmingham Business School",
                    "Voters": 3,
                    "NonVoters": 430,
                    "Eligible": 433,
                    "IsOtherItem": false,
                    "Turnout": 0.69284064665127,
                    "RelativeTurnout": 0.00732690194162902
                },
                {
                    "Name": "Birmingham International Acad",
                    "Voters": 4,
                    "NonVoters": 514,
                    "Eligible": 518,
                    "IsOtherItem": false,
                    "Turnout": 0.772200772200772,
                    "RelativeTurnout": 0.00976920258883869
                },
                {
                    "Name": "Birmingham Leadership Inst",
                    "Voters": 0,
                    "NonVoters": 0,
                    "Eligible": 0,
                    "IsOtherItem": false,
                    "Turnout": 0.0,
                    "RelativeTurnout": 0.0
                },
                {
                    "Name": "Birmingham Medical School",
                    "Voters": 10,
                    "NonVoters": 2289,
                    "Eligible": 2299,
                    "IsOtherItem": false,
                    "Turnout": 0.434971726837756,
                    "RelativeTurnout": 0.0244230064720967
                },
                {
                    "Name": "Byzantine, Ottoman, Greek Stud",
                    "Voters": 0,
                    "NonVoters": 9,
                    "Eligible": 9,
                    "IsOtherItem": false,
                    "Turnout": 0.0,
                    "RelativeTurnout": 0.0
                },
                {
                    "Name": "Chemical Engineering",
                    "Voters": 14,
                    "NonVoters": 859,
                    "Eligible": 873,
                    "IsOtherItem": false,
                    "Turnout": 1.60366552119129,
                    "RelativeTurnout": 0.0341922090609354
                },
                {
                    "Name": "Chemistry",
                    "Voters": 5,
                    "NonVoters": 554,
                    "Eligible": 559,
                    "IsOtherItem": false,
                    "Turnout": 0.894454382826476,
                    "RelativeTurnout": 0.0122115032360484
                },
                {
                    "Name": "Civil Engineering",
                    "Voters": 5,
                    "NonVoters": 551,
                    "Eligible": 556,
                    "IsOtherItem": false,
                    "Turnout": 0.899280575539568,
                    "RelativeTurnout": 0.0122115032360484
                },
                {
                    "Name": "Classics, AH and Archaeology",
                    "Voters": 4,
                    "NonVoters": 256,
                    "Eligible": 260,
                    "IsOtherItem": false,
                    "Turnout": 1.53846153846154,
                    "RelativeTurnout": 0.00976920258883869
                },
                {
                    "Name": "Computer Science",
                    "Voters": 61,
                    "NonVoters": 2239,
                    "Eligible": 2300,
                    "IsOtherItem": false,
                    "Turnout": 2.65217391304348,
                    "RelativeTurnout": 0.14898033947979
                },
                {
                    "Name": "COS - College Hub",
                    "Voters": 1,
                    "NonVoters": 20,
                    "Eligible": 21,
                    "IsOtherItem": false,
                    "Turnout": 4.76190476190476,
                    "RelativeTurnout": 0.00244230064720967
                },
                {
                    "Name": "Dental Hygiene and Therapy",
                    "Voters": 0,
                    "NonVoters": 82,
                    "Eligible": 82,
                    "IsOtherItem": false,
                    "Turnout": 0.0,
                    "RelativeTurnout": 0.0
                },
                {
                    "Name": "Dentistry",
                    "Voters": 1,
                    "NonVoters": 448,
                    "Eligible": 449,
                    "IsOtherItem": false,
                    "Turnout": 0.22271714922049,
                    "RelativeTurnout": 0.00244230064720967
                },
                {
                    "Name": "Disab, Inclusion & Spec Needs",
                    "Voters": 4,
                    "NonVoters": 781,
                    "Eligible": 785,
                    "IsOtherItem": false,
                    "Turnout": 0.509554140127388,
                    "RelativeTurnout": 0.00976920258883869
                },
                {
                    "Name": "Drama and Theatre Arts",
                    "Voters": 0,
                    "NonVoters": 134,
                    "Eligible": 134,
                    "IsOtherItem": false,
                    "Turnout": 0.0,
                    "RelativeTurnout": 0.0
                },
                {
                    "Name": "Earth and Environ Sciences",
                    "Voters": 18,
                    "NonVoters": 492,
                    "Eligible": 510,
                    "IsOtherItem": false,
                    "Turnout": 3.52941176470588,
                    "RelativeTurnout": 0.0439614116497741
                },
                {
                    "Name": "Economics",
                    "Voters": 25,
                    "NonVoters": 1415,
                    "Eligible": 1440,
                    "IsOtherItem": false,
                    "Turnout": 1.73611111111111,
                    "RelativeTurnout": 0.0610575161802418
                },
                {
                    "Name": "Education & Social Justice",
                    "Voters": 3,
                    "NonVoters": 582,
                    "Eligible": 585,
                    "IsOtherItem": false,
                    "Turnout": 0.512820512820513,
                    "RelativeTurnout": 0.00732690194162902
                },
                {
                    "Name": "Elec, Elec & Sys Engineering",
                    "Voters": 11,
                    "NonVoters": 637,
                    "Eligible": 648,
                    "IsOtherItem": false,
                    "Turnout": 1.69753086419753,
                    "RelativeTurnout": 0.0268653071193064
                },
                {
                    "Name": "Eng Lang and Linguistics",
                    "Voters": 1,
                    "NonVoters": 474,
                    "Eligible": 475,
                    "IsOtherItem": false,
                    "Turnout": 0.210526315789474,
                    "RelativeTurnout": 0.00244230064720967
                },
                {
                    "Name": "Engineering",
                    "Voters": 30,
                    "NonVoters": 224,
                    "Eligible": 254,
                    "IsOtherItem": false,
                    "Turnout": 11.8110236220472,
                    "RelativeTurnout": 0.0732690194162901
                },
                {
                    "Name": "English Literature",
                    "Voters": 4,
                    "NonVoters": 590,
                    "Eligible": 594,
                    "IsOtherItem": false,
                    "Turnout": 0.673400673400673,
                    "RelativeTurnout": 0.00976920258883869
                },
                {
                    "Name": "EPS - College Hub",
                    "Voters": 2,
                    "NonVoters": 125,
                    "Eligible": 127,
                    "IsOtherItem": false,
                    "Turnout": 1.5748031496063,
                    "RelativeTurnout": 0.00488460129441934
                },
                {
                    "Name": "Film and Creative Writing",
                    "Voters": 6,
                    "NonVoters": 377,
                    "Eligible": 383,
                    "IsOtherItem": false,
                    "Turnout": 1.56657963446475,
                    "RelativeTurnout": 0.014653803883258
                },
                {
                    "Name": "Finance",
                    "Voters": 7,
                    "NonVoters": 253,
                    "Eligible": 260,
                    "IsOtherItem": false,
                    "Turnout": 2.69230769230769,
                    "RelativeTurnout": 0.0170961045304677
                },
                {
                    "Name": "Geography",
                    "Voters": 10,
                    "NonVoters": 800,
                    "Eligible": 810,
                    "IsOtherItem": false,
                    "Turnout": 1.23456790123457,
                    "RelativeTurnout": 0.0244230064720967
                },
                {
                    "Name": "Golf Studies",
                    "Voters": 0,
                    "NonVoters": 691,
                    "Eligible": 691,
                    "IsOtherItem": false,
                    "Turnout": 0.0,
                    "RelativeTurnout": 0.0
                },
                {
                    "Name": "Health Services Management Cen",
                    "Voters": 4,
                    "NonVoters": 746,
                    "Eligible": 750,
                    "IsOtherItem": false,
                    "Turnout": 0.533333333333333,
                    "RelativeTurnout": 0.00976920258883869
                },
                {
                    "Name": "HEFi",
                    "Voters": 0,
                    "NonVoters": 13,
                    "Eligible": 13,
                    "IsOtherItem": false,
                    "Turnout": 0.0,
                    "RelativeTurnout": 0.0
                },
                {
                    "Name": "History",
                    "Voters": 21,
                    "NonVoters": 818,
                    "Eligible": 839,
                    "IsOtherItem": false,
                    "Turnout": 2.50297973778308,
                    "RelativeTurnout": 0.0512883135914031
                },
                {
                    "Name": "Inst of Applied Health Res",
                    "Voters": 7,
                    "NonVoters": 251,
                    "Eligible": 258,
                    "IsOtherItem": false,
                    "Turnout": 2.71317829457364,
                    "RelativeTurnout": 0.0170961045304677
                },
                {
                    "Name": "Inst of Cancer / Genomic Sci",
                    "Voters": 3,
                    "NonVoters": 287,
                    "Eligible": 290,
                    "IsOtherItem": false,
                    "Turnout": 1.03448275862069,
                    "RelativeTurnout": 0.00732690194162902
                },
                {
                    "Name": "Inst of Card Sciences",
                    "Voters": 0,
                    "NonVoters": 56,
                    "Eligible": 56,
                    "IsOtherItem": false,
                    "Turnout": 0.0,
                    "RelativeTurnout": 0.0
                },
                {
                    "Name": "Inst of Immunol + Immunoth",
                    "Voters": 1,
                    "NonVoters": 108,
                    "Eligible": 109,
                    "IsOtherItem": false,
                    "Turnout": 0.91743119266055,
                    "RelativeTurnout": 0.00244230064720967
                },
                {
                    "Name": "Inst of Inflammation / Ageing",
                    "Voters": 0,
                    "NonVoters": 82,
                    "Eligible": 82,
                    "IsOtherItem": false,
                    "Turnout": 0.0,
                    "RelativeTurnout": 0.0
                },
                {
                    "Name": "Inst of Metabolism and Sys Res",
                    "Voters": 0,
                    "NonVoters": 39,
                    "Eligible": 39,
                    "IsOtherItem": false,
                    "Turnout": 0.0,
                    "RelativeTurnout": 0.0
                },
                {
                    "Name": "Inst of Microb and Infection",
                    "Voters": 0,
                    "NonVoters": 26,
                    "Eligible": 26,
                    "IsOtherItem": false,
                    "Turnout": 0.0,
                    "RelativeTurnout": 0.0
                },
                {
                    "Name": "Institute of Clinical Sciences",
                    "Voters": 0,
                    "NonVoters": 9,
                    "Eligible": 9,
                    "IsOtherItem": false,
                    "Turnout": 0.0,
                    "RelativeTurnout": 0.0
                },
                {
                    "Name": "International Development",
                    "Voters": 3,
                    "NonVoters": 406,
                    "Eligible": 409,
                    "IsOtherItem": false,
                    "Turnout": 0.733496332518338,
                    "RelativeTurnout": 0.00732690194162902
                },
                {
                    "Name": "Law",
                    "Voters": 66,
                    "NonVoters": 1883,
                    "Eligible": 1949,
                    "IsOtherItem": false,
                    "Turnout": 3.38635197537199,
                    "RelativeTurnout": 0.161191842715838
                },
                {
                    "Name": "Liberal Arts & Natural Science",
                    "Voters": 7,
                    "NonVoters": 405,
                    "Eligible": 412,
                    "IsOtherItem": false,
                    "Turnout": 1.69902912621359,
                    "RelativeTurnout": 0.0170961045304677
                },
                {
                    "Name": "Management",
                    "Voters": 19,
                    "NonVoters": 2329,
                    "Eligible": 2348,
                    "IsOtherItem": false,
                    "Turnout": 0.809199318568995,
                    "RelativeTurnout": 0.0464037122969838
                },
                {
                    "Name": "Marketing",
                    "Voters": 7,
                    "NonVoters": 261,
                    "Eligible": 268,
                    "IsOtherItem": false,
                    "Turnout": 2.61194029850746,
                    "RelativeTurnout": 0.0170961045304677
                },
                {
                    "Name": "Mathematics",
                    "Voters": 11,
                    "NonVoters": 1739,
                    "Eligible": 1750,
                    "IsOtherItem": false,
                    "Turnout": 0.628571428571429,
                    "RelativeTurnout": 0.0268653071193064
                },
                {
                    "Name": "MDS - College Hub",
                    "Voters": 0,
                    "NonVoters": 6,
                    "Eligible": 6,
                    "IsOtherItem": false,
                    "Turnout": 0.0,
                    "RelativeTurnout": 0.0
                },
                {
                    "Name": "Mechanical Engineering",
                    "Voters": 13,
                    "NonVoters": 849,
                    "Eligible": 862,
                    "IsOtherItem": false,
                    "Turnout": 1.50812064965197,
                    "RelativeTurnout": 0.0317499084137257
                },
                {
                    "Name": "Metallurgy & Materials",
                    "Voters": 2,
                    "NonVoters": 499,
                    "Eligible": 501,
                    "IsOtherItem": false,
                    "Turnout": 0.399201596806387,
                    "RelativeTurnout": 0.00488460129441934
                },
                {
                    "Name": "Modern Languages",
                    "Voters": 4,
                    "NonVoters": 549,
                    "Eligible": 553,
                    "IsOtherItem": false,
                    "Turnout": 0.723327305605786,
                    "RelativeTurnout": 0.00976920258883869
                },
                {
                    "Name": "Music",
                    "Voters": 3,
                    "NonVoters": 194,
                    "Eligible": 197,
                    "IsOtherItem": false,
                    "Turnout": 1.52284263959391,
                    "RelativeTurnout": 0.00732690194162902
                },
                {
                    "Name": "Nursing and Midwifery",
                    "Voters": 4,
                    "NonVoters": 901,
                    "Eligible": 905,
                    "IsOtherItem": false,
                    "Turnout": 0.441988950276243,
                    "RelativeTurnout": 0.00976920258883869
                },
                {
                    "Name": "People and Organisational Deve",
                    "Voters": 0,
                    "NonVoters": 48,
                    "Eligible": 48,
                    "IsOtherItem": false,
                    "Turnout": 0.0,
                    "RelativeTurnout": 0.0
                },
                {
                    "Name": "Pharmacy",
                    "Voters": 2,
                    "NonVoters": 541,
                    "Eligible": 543,
                    "IsOtherItem": false,
                    "Turnout": 0.368324125230203,
                    "RelativeTurnout": 0.00488460129441934
                },
                {
                    "Name": "Philosophy",
                    "Voters": 6,
                    "NonVoters": 380,
                    "Eligible": 386,
                    "IsOtherItem": false,
                    "Turnout": 1.55440414507772,
                    "RelativeTurnout": 0.014653803883258
                },
                {
                    "Name": "Physics & Astronomy",
                    "Voters": 16,
                    "NonVoters": 765,
                    "Eligible": 781,
                    "IsOtherItem": false,
                    "Turnout": 2.04865556978233,
                    "RelativeTurnout": 0.0390768103553548
                },
                {
                    "Name": "Physiotherapy",
                    "Voters": 1,
                    "NonVoters": 401,
                    "Eligible": 402,
                    "IsOtherItem": false,
                    "Turnout": 0.248756218905473,
                    "RelativeTurnout": 0.00244230064720967
                },
                {
                    "Name": "Political Sci & Intern'tl Stud",
                    "Voters": 26,
                    "NonVoters": 879,
                    "Eligible": 905,
                    "IsOtherItem": false,
                    "Turnout": 2.87292817679558,
                    "RelativeTurnout": 0.0634998168274514
                },
                {
                    "Name": "School of Biosciences",
                    "Voters": 19,
                    "NonVoters": 1154,
                    "Eligible": 1173,
                    "IsOtherItem": false,
                    "Turnout": 1.61977834612106,
                    "RelativeTurnout": 0.0464037122969838
                },
                {
                    "Name": "School of Education",
                    "Voters": 1,
                    "NonVoters": 89,
                    "Eligible": 90,
                    "IsOtherItem": false,
                    "Turnout": 1.11111111111111,
                    "RelativeTurnout": 0.00244230064720967
                },
                {
                    "Name": "School of Psychology",
                    "Voters": 16,
                    "NonVoters": 1654,
                    "Eligible": 1670,
                    "IsOtherItem": false,
                    "Turnout": 0.958083832335329,
                    "RelativeTurnout": 0.0390768103553548
                },
                {
                    "Name": "Shakespeare Institute",
                    "Voters": 1,
                    "NonVoters": 134,
                    "Eligible": 135,
                    "IsOtherItem": false,
                    "Turnout": 0.740740740740741,
                    "RelativeTurnout": 0.00244230064720967
                },
                {
                    "Name": "Soc Policy, Sociology & Crimin",
                    "Voters": 10,
                    "NonVoters": 855,
                    "Eligible": 865,
                    "IsOtherItem": false,
                    "Turnout": 1.15606936416185,
                    "RelativeTurnout": 0.0244230064720967
                },
                {
                    "Name": "Social Work & Social Care",
                    "Voters": 2,
                    "NonVoters": 328,
                    "Eligible": 330,
                    "IsOtherItem": false,
                    "Turnout": 0.606060606060606,
                    "RelativeTurnout": 0.00488460129441934
                },
                {
                    "Name": "Sport, Ex and Rehab Sciences",
                    "Voters": 6,
                    "NonVoters": 1017,
                    "Eligible": 1023,
                    "IsOtherItem": false,
                    "Turnout": 0.586510263929619,
                    "RelativeTurnout": 0.014653803883258
                },
                {
                    "Name": "Strategy and Int Business",
                    "Voters": 6,
                    "NonVoters": 275,
                    "Eligible": 281,
                    "IsOtherItem": false,
                    "Turnout": 2.13523131672598,
                    "RelativeTurnout": 0.014653803883258
                },
                {
                    "Name": "Teacher Education",
                    "Voters": 1,
                    "NonVoters": 506,
                    "Eligible": 507,
                    "IsOtherItem": false,
                    "Turnout": 0.19723865877712,
                    "RelativeTurnout": 0.00244230064720967
                },
                {
                    "Name": "Theology and Religion",
                    "Voters": 4,
                    "NonVoters": 295,
                    "Eligible": 299,
                    "IsOtherItem": false,
                    "Turnout": 1.33779264214047,
                    "RelativeTurnout": 0.00976920258883869
                },
                {
                    "Name": "Urdang Academy",
                    "Voters": 0,
                    "NonVoters": 119,
                    "Eligible": 119,
                    "IsOtherItem": false,
                    "Turnout": 0.0,
                    "RelativeTurnout": 0.0
                },
                {
                    "Name": "Wiley",
                    "Voters": 0,
                    "NonVoters": 572,
                    "Eligible": 572,
                    "IsOtherItem": false,
                    "Turnout": 0.0,
                    "RelativeTurnout": 0.0
                }
            ]
        }
    ],
    "Turnout": 1.34814995725974
}